rt_range/__init__.py
rt_range/common.py
rt_range/ethernet/__init__.py
rt_range/ethernet/eth_parser.py
rt_range/ethernet/rt_packet.py
rt_range/ethernet/rt_types.py
rt_range/ethernet/status_definitions.py
rt_range/ethernet/ncom/__init__.py
rt_range/ethernet/ncom/batch_s.py
rt_range/ethernet/ncom/ncom.py
rt_range/ethernet/rcom/__init__.py
rt_range/ethernet/rcom/extended_range_packet.py
rt_range/ethernet/rcom/lane_packet.py
rt_range/ethernet/rcom/wrapped_ncom_packet.py
rt_range-0.3.2.dist-info/LICENSE.txt
rt_range-0.3.2.dist-info/METADATA
rt_range-0.3.2.dist-info/WHEEL
rt_range-0.3.2.dist-info/top_level.txt
rt_range-0.3.2.dist-info/RECORD
