Metadata-Version: 2.1
Name: rt_range
Version: 0.3.2
Summary: OxTS RT-Range data parsing utility
License: MIT License
Requires-Python: >=3.10
License-File: LICENSE.txt
Requires-Dist: numpy >=1.22.0 ; python_version == "3.10"
Requires-Dist: numpy >=1.24.0 ; python_version == "3.11"
